video_behavior_tracking/LED_detection.py
video_behavior_tracking/__init__.py
video_behavior_tracking/kalman.py
video_behavior_tracking/labeled_video.py
video_behavior_tracking/track_behavior.py
video_behavior_tracking/utils.py
video_behavior_tracking-0.1.8.dev0.dist-info/LICENSE
video_behavior_tracking-0.1.8.dev0.dist-info/METADATA
video_behavior_tracking-0.1.8.dev0.dist-info/WHEEL
video_behavior_tracking-0.1.8.dev0.dist-info/entry_points.txt
video_behavior_tracking-0.1.8.dev0.dist-info/top_level.txt
video_behavior_tracking-0.1.8.dev0.dist-info/RECORD
