Metadata-Version: 2.1
Name: video-behavior-tracking
Version: 0.1.8.dev0
Summary: Extract behavior from video
Home-page: https://github.com/Eden-Kramer-Lab/video_behavior_tracking
Author: Eric Denovellis
Author-email: edeno@bu.edu
License: MIT
Platform: UNKNOWN
Requires-Dist: numpy (>=1.11)
Requires-Dist: scipy
Requires-Dist: pandas
Requires-Dist: opencv-python
Requires-Dist: tqdm
